pyliteinfo/__init__.py
pyliteinfo/info.py
pyliteinfo-0.1.0.dist-info/METADATA
pyliteinfo-0.1.0.dist-info/WHEEL
pyliteinfo-0.1.0.dist-info/top_level.txt
pyliteinfo-0.1.0.dist-info/RECORD
