Metadata-Version: 2.4
Name: pyliteinfo
Version: 0.1.0
Summary: Lightweight system and storage info utility in Python
Author: Your Name
Requires-Python: >=3.6
Requires-Dist: psutil
Dynamic: author
Dynamic: requires-dist
Dynamic: requires-python
Dynamic: summary
